<?xml version="1.0" encoding="UTF-8"?>
<DEFECTS>
<OACRDEFECTCOUNT>17</OACRDEFECTCOUNT>
<OACRERRORCOUNT>0</OACRERRORCOUNT>
<DEFECT _seq="1"><SFA><LINE>35</LINE><COLUMN>20</COLUMN><FILENAME>driverentry.cpp</FILENAME><FILEPATH>f:\usbfilter\usbfilter\</FILEPATH></SFA><DEFECTCODE>28101</DEFECTCODE><DESCRIPTION>The Drivers module has inferred that the current function is a DRIVER_INITIALIZE function:  This is informational only. No problem has been detected.</DESCRIPTION><FUNCTION>DriverEntry</FUNCTION><FUNCLINE>35</FUNCLINE><PATH/></DEFECT>
<DEFECT _seq="2"><SFA><LINE>47</LINE><COLUMN>43</COLUMN><FILENAME>driverentry.cpp</FILENAME><FILEPATH>f:\usbfilter\usbfilter\</FILEPATH></SFA><DEFECTCODE>28169</DEFECTCODE><DESCRIPTION>The dispatch function 'DispatchPower' does not have any __drv_dispatchType annotations:  This can be corrected by adding appropriate __drv_dispatchType annotations to the function. Unnecessary casts can cause this warning.</DESCRIPTION><FUNCTION>DriverEntry</FUNCTION><FUNCLINE>35</FUNCLINE><PATH/></DEFECT>
<DEFECT _seq="3"><SFA><LINE>48</LINE><COLUMN>41</COLUMN><FILENAME>driverentry.cpp</FILENAME><FILEPATH>f:\usbfilter\usbfilter\</FILEPATH></SFA><DEFECTCODE>28169</DEFECTCODE><DESCRIPTION>The dispatch function 'DispatchPnp' does not have any __drv_dispatchType annotations:  This can be corrected by adding appropriate __drv_dispatchType annotations to the function. Unnecessary casts can cause this warning.</DESCRIPTION><FUNCTION>DriverEntry</FUNCTION><FUNCLINE>35</FUNCLINE><PATH/></DEFECT>
<DEFECT _seq="4"><SFA><LINE>49</LINE><COLUMN>42</COLUMN><FILENAME>driverentry.cpp</FILENAME><FILEPATH>f:\usbfilter\usbfilter\</FILEPATH></SFA><DEFECTCODE>28169</DEFECTCODE><DESCRIPTION>The dispatch function 'DispatchForSCSI' does not have any __drv_dispatchType annotations:  This can be corrected by adding appropriate __drv_dispatchType annotations to the function. Unnecessary casts can cause this warning.</DESCRIPTION><FUNCTION>DriverEntry</FUNCTION><FUNCLINE>35</FUNCLINE><PATH/></DEFECT>
<DEFECT _seq="5"><SFA><LINE>45</LINE><COLUMN>33</COLUMN><FILENAME>driverentry.cpp</FILENAME><FILEPATH>f:\usbfilter\usbfilter\</FILEPATH></SFA><DEFECTCODE>28169</DEFECTCODE><DESCRIPTION>The dispatch function 'DispatchAny' does not have any __drv_dispatchType annotations:  This can be corrected by adding appropriate __drv_dispatchType annotations to the function. Unnecessary casts can cause this warning.</DESCRIPTION><FUNCTION>DriverEntry</FUNCTION><FUNCLINE>35</FUNCLINE><PATH/></DEFECT>
<DEFECT _seq="6"><SFA><LINE>41</LINE><COLUMN>28</COLUMN><FILENAME>driverentry.cpp</FILENAME><FILEPATH>f:\usbfilter\usbfilter\</FILEPATH></SFA><DEFECTCODE>28155</DEFECTCODE><DESCRIPTION>The function being assigned or passed should be a DRIVER_UNLOAD function:  Add the declaration 'DRIVER_UNLOAD DriverUnload;' before the current first declaration of DriverUnload.</DESCRIPTION><FUNCTION>DriverEntry</FUNCTION><FUNCLINE>35</FUNCLINE><PATH/></DEFECT>
<DEFECT _seq="7"><SFA><LINE>42</LINE><COLUMN>42</COLUMN><FILENAME>driverentry.cpp</FILENAME><FILEPATH>f:\usbfilter\usbfilter\</FILEPATH></SFA><DEFECTCODE>28155</DEFECTCODE><DESCRIPTION>The function being assigned or passed should be a DRIVER_ADD_DEVICE function:  Add the declaration 'DRIVER_ADD_DEVICE AddDevice;' before the current first declaration of AddDevice.</DESCRIPTION><FUNCTION>DriverEntry</FUNCTION><FUNCLINE>35</FUNCLINE><PATH/></DEFECT>
<DEFECT _seq="8"><SFA><LINE>45</LINE><COLUMN>33</COLUMN><FILENAME>driverentry.cpp</FILENAME><FILEPATH>f:\usbfilter\usbfilter\</FILEPATH></SFA><DEFECTCODE>28155</DEFECTCODE><DESCRIPTION>The function being assigned or passed should be a DRIVER_DISPATCH function:  Add the declaration 'DRIVER_DISPATCH DispatchAny;' before the current first declaration of DispatchAny.</DESCRIPTION><FUNCTION>DriverEntry</FUNCTION><FUNCLINE>35</FUNCLINE><PATH/></DEFECT>
<DEFECT _seq="9"><SFA><LINE>47</LINE><COLUMN>43</COLUMN><FILENAME>driverentry.cpp</FILENAME><FILEPATH>f:\usbfilter\usbfilter\</FILEPATH></SFA><DEFECTCODE>28155</DEFECTCODE><DESCRIPTION>The function being assigned or passed should be a DRIVER_DISPATCH function:  Add the declaration 'DRIVER_DISPATCH DispatchPower;' before the current first declaration of DispatchPower.</DESCRIPTION><FUNCTION>DriverEntry</FUNCTION><FUNCLINE>35</FUNCLINE><PATH/></DEFECT>
<DEFECT _seq="10"><SFA><LINE>48</LINE><COLUMN>41</COLUMN><FILENAME>driverentry.cpp</FILENAME><FILEPATH>f:\usbfilter\usbfilter\</FILEPATH></SFA><DEFECTCODE>28155</DEFECTCODE><DESCRIPTION>The function being assigned or passed should be a DRIVER_DISPATCH function:  Add the declaration 'DRIVER_DISPATCH DispatchPnp;' before the current first declaration of DispatchPnp.</DESCRIPTION><FUNCTION>DriverEntry</FUNCTION><FUNCLINE>35</FUNCLINE><PATH/></DEFECT>
<DEFECT _seq="11"><SFA><LINE>49</LINE><COLUMN>42</COLUMN><FILENAME>driverentry.cpp</FILENAME><FILEPATH>f:\usbfilter\usbfilter\</FILEPATH></SFA><DEFECTCODE>28155</DEFECTCODE><DESCRIPTION>The function being assigned or passed should be a DRIVER_DISPATCH function:  Add the declaration 'DRIVER_DISPATCH DispatchForSCSI;' before the current first declaration of DispatchForSCSI.</DESCRIPTION><FUNCTION>DriverEntry</FUNCTION><FUNCLINE>35</FUNCLINE><PATH/></DEFECT>
<DEFECT _seq="12"><SFA><LINE>221</LINE><COLUMN>7</COLUMN><FILENAME>driverentry.cpp</FILENAME><FILEPATH>f:\usbfilter\usbfilter\</FILEPATH></SFA><DEFECTCODE>28155</DEFECTCODE><DESCRIPTION>The function being assigned or passed should be a IO_COMPLETION_ROUTINE function:  Add the declaration 'IO_COMPLETION_ROUTINE USBSCSICompletion;' before the current first declaration of USBSCSICompletion.</DESCRIPTION><FUNCTION>DispatchForSCSI</FUNCTION><FUNCLINE>195</FUNCLINE><PATH/></DEFECT>
<DEFECT _seq="13"><SFA><LINE>460</LINE><COLUMN>13</COLUMN><FILENAME>driverentry.cpp</FILENAME><FILEPATH>f:\usbfilter\usbfilter\</FILEPATH></SFA><DEFECTCODE>28175</DEFECTCODE><DESCRIPTION>The 'AttachedDevice' member of _DEVICE_OBJECT should not be accessed by a driver:  Access to this member may be permitted for certain classes of drivers. See the documentation for this warning for more information.</DESCRIPTION><FUNCTION>DispatchPnp</FUNCTION><FUNCLINE>402</FUNCLINE><PATH/></DEFECT>
<DEFECT _seq="14"><SFA><LINE>460</LINE><COLUMN>38</COLUMN><FILENAME>driverentry.cpp</FILENAME><FILEPATH>f:\usbfilter\usbfilter\</FILEPATH></SFA><DEFECTCODE>28175</DEFECTCODE><DESCRIPTION>The 'AttachedDevice' member of _DEVICE_OBJECT should not be accessed by a driver:  Access to this member may be permitted for certain classes of drivers. See the documentation for this warning for more information.</DESCRIPTION><FUNCTION>DispatchPnp</FUNCTION><FUNCLINE>402</FUNCLINE><PATH/></DEFECT>
<DEFECT _seq="15"><SFA><LINE>467</LINE><COLUMN>55</COLUMN><FILENAME>driverentry.cpp</FILENAME><FILEPATH>f:\usbfilter\usbfilter\</FILEPATH></SFA><DEFECTCODE>28155</DEFECTCODE><DESCRIPTION>The function being assigned or passed should be a IO_COMPLETION_ROUTINE function:  Add the declaration 'IO_COMPLETION_ROUTINE UsageNotificationCompletionRoutine;' before the current first declaration of UsageNotificationCompletionRoutine.</DESCRIPTION><FUNCTION>DispatchPnp</FUNCTION><FUNCLINE>402</FUNCLINE><PATH/></DEFECT>
<DEFECT _seq="16"><SFA><LINE>476</LINE><COLUMN>55</COLUMN><FILENAME>driverentry.cpp</FILENAME><FILEPATH>f:\usbfilter\usbfilter\</FILEPATH></SFA><DEFECTCODE>28155</DEFECTCODE><DESCRIPTION>The function being assigned or passed should be a IO_COMPLETION_ROUTINE function:  Add the declaration 'IO_COMPLETION_ROUTINE StartDeviceCompletionRoutine;' before the current first declaration of StartDeviceCompletionRoutine.</DESCRIPTION><FUNCTION>DispatchPnp</FUNCTION><FUNCLINE>402</FUNCLINE><PATH/></DEFECT>
<DEFECT _seq="17"><SFA><LINE>508</LINE><COLUMN>6</COLUMN><FILENAME>driverentry.cpp</FILENAME><FILEPATH>f:\usbfilter\usbfilter\</FILEPATH></SFA><DEFECTCODE>28170</DEFECTCODE><DESCRIPTION>The function 'GetDeviceTypeToUse' has been declared to be in a paged segment, but neither PAGED_CODE nor PAGED_CODE_LOCKED was found.</DESCRIPTION><FUNCTION>GetDeviceTypeToUse</FUNCTION><FUNCLINE>508</FUNCLINE><PATH/></DEFECT>
</DEFECTS>
